{
    "Assets":"Assets",
    "App - Assets":"App - Assets",
    "Add asset":"Add asset",
    "Restore asset":"Restore asset",
    "ID":"ID",
    "Name":"Name",
    "Source from file":"Source from file",
    "File":"File",
    "Source from database":"Source from database",
    "Database":"Database",
    "Development":"Development",
    "Use in development":"Use in development",
    "Production":"Production",
    "Use in production":"Use in production",
    "Eval":"Eval",
    "PHP Eval (Danger Zone)":"PHP Eval (Danger Zone)",
    "Active":"Active",
    "Edit":"Edit",
    "Delete":"Delete",
    "Add language":"Add language",
    "Move":"Move",
    "Edit asset":"Edit asset",
    "Cancel":"Cancel",
    "Save":"Save",
    "Restore previous version":"Restore previous version",
    "Author: ":"Author: ",
    "Last edit: ":"Last edit: ",
    "Date: ":"Date: "
}